MANIFEST.in
README.txt
TODO.txt
setup.py
collective/__init__.py
collective.seobatching.egg-info/PKG-INFO
collective.seobatching.egg-info/SOURCES.txt
collective.seobatching.egg-info/dependency_links.txt
collective.seobatching.egg-info/entry_points.txt
collective.seobatching.egg-info/namespace_packages.txt
collective.seobatching.egg-info/not-zip-safe
collective.seobatching.egg-info/paster_plugins.txt
collective.seobatching.egg-info/requires.txt
collective.seobatching.egg-info/top_level.txt
collective/seobatching/__init__.py
collective/seobatching/config.py
collective/seobatching/configure.zcml
collective/seobatching/interfaces.py
collective/seobatching/traversal.py
collective/seobatching/browser/__init__.py
collective/seobatching/browser/batching.py
collective/seobatching/browser/configure.zcml
collective/seobatching/profiles/default/metadata.xml
collective/seobatching/profiles/default/propertiestool.xml
collective/seobatching/profiles/default/skins.xml
collective/seobatching/skins/collective_seobatching/seo_batch_macros.pt
collective/seobatching/tests/__init__.py
collective/seobatching/tests/base.py
collective/seobatching/tests/test_seobatching_view.py
collective/seobatching/tests/test_setup.py
collective/seobatching/tests/test_traversal.py
docs/HISTORY.txt
docs/INSTALL.txt
docs/LICENSE.GPL
docs/LICENSE.txt