Metadata-Version: 1.0
Name: collective.seobatching
Version: 1.0
Summary: This package replaces query parameters from batched listings thus making them more seo friendly.
Home-page: http://svn.plone.org/svn/collective/collective.seobatching
Author: Vitaliy Podoba
Author-email: vitaliypodoba@gmail.com
License: GPL
Keywords: batching seo plone
Platform: UNKNOWN
Classifier: Framework :: Plone
Classifier: Programming Language :: Python
